[
    {
        "title": "Happy",
        "artist": "Pharrell Williams",
        "year": 2014,
        "youtubeId": "y6Sxv-sUYtM",
        "startTime": 54
    },
    {
        "title": "Dark Horse",
        "artist": "Katy Perry featuring Juicy J",
        "year": 2014,
        "youtubeId": "0KSOMA3QBU0",
        "startTime": 49
    },
    {
        "title": "All of Me",
        "artist": "John Legend",
        "year": 2014,
        "youtubeId": "450p7goxZqg",
        "startTime": 50
    },
    {
        "title": "Fancy",
        "artist": "Iggy Azalea featuring Charli XCX",
        "year": 2014,
        "youtubeId": "O-zpOMYRi0w",
        "startTime": 49
    },
    {
        "title": "Counting Stars",
        "artist": "OneRepublic",
        "year": 2014,
        "youtubeId": "hT_nvWreIhg",
        "startTime": 77
    },
    {
        "title": "Talk Dirty",
        "artist": "Jason Derulo featuring 2 Chainz",
        "year": 2014,
        "youtubeId": "RbtPXFlZlHg",
        "startTime": 34
    },
    {
        "title": "Rude",
        "artist": "Magic!",
        "year": 2014,
        "youtubeId": "PIh2xe4jnpk",
        "startTime": 54
    },
    {
        "title": "All About That Bass",
        "artist": "Meghan Trainor",
        "year": 2014,
        "youtubeId": "7PCk64g9c6I",
        "startTime": 40
    },
    {
        "title": "Problem",
        "artist": "Ariana Grande featuring Iggy Azalea",
        "year": 2014,
        "youtubeId": "iS1g8sjmf4g",
        "startTime": 54
    },
    {
        "title": "Stay with Me",
        "artist": "Sam Smith",
        "year": 2014,
        "youtubeId": "pB-5XG-Kpl4",
        "startTime": 58
    },
    {
        "title": "Timber",
        "artist": "Pitbull featuring Kesha",
        "year": 2014,
        "youtubeId": "hHUbLv4rlsU",
        "startTime": 21
    },
    {
        "title": "Pompeii",
        "artist": "Bastille",
        "year": 2014,
        "youtubeId": "F90Cw4l-8NY",
        "startTime": 41
    },
    {
        "title": "Shake It Off",
        "artist": "Taylor Swift",
        "year": 2014,
        "youtubeId": "nfWlot6h_JM",
        "startTime": 29
    },
    {
        "title": "Am I Wrong",
        "artist": "Nico & Vinz",
        "year": 2014,
        "youtubeId": "bg1sT4ILG0w",
        "startTime": 40
    },
    {
        "title": "Turn Down for What",
        "artist": "DJ Snake and Lil Jon",
        "year": 2014,
        "youtubeId": "HMUDVMiITOU",
        "startTime": 8
    },
    {
        "title": "The Monster",
        "artist": "Eminem featuring Rihanna",
        "year": 2014,
        "youtubeId": "EHkozMIXZ8w",
        "startTime": 28
    },
    {
        "title": "Say Something",
        "artist": "A Great Big World and Christina Aguilera",
        "year": 2014,
        "youtubeId": "-2U0Ivkn2Ds",
        "startTime": 54
    },
    {
        "title": "Team",
        "artist": "Lorde",
        "year": 2014,
        "youtubeId": "f2JuxM-NGsY",
        "startTime": 50
    },
    {
        "title": "Let Her Go",
        "artist": "Passenger",
        "year": 2014,
        "youtubeId": "RBumgq5yVrA",
        "startTime": 45
    },
    {
        "title": "Royals",
        "artist": "Lorde",
        "year": 2014,
        "youtubeId": "nlcKzY4o92g",
        "startTime": 49
    },
    {
        "title": "Let It Go",
        "artist": "Idina Menzel",
        "year": 2014,
        "youtubeId": "L0MK7qz13bU",
        "startTime": 48
    },
    {
        "title": "Wake Me Up",
        "artist": "Avicii",
        "year": 2014,
        "youtubeId": "IcrbM1l_BoI",
        "startTime": 65
    },
    {
        "title": "Demons",
        "artist": "Imagine Dragons",
        "year": 2014,
        "youtubeId": "mWRsgZuwf_8",
        "startTime": 40
    },
    {
        "title": "Story of My Life",
        "artist": "One Direction",
        "year": 2014,
        "youtubeId": "W-TE_Ys4my4",
        "startTime": 87
    },
    {
        "title": "Chandelier",
        "artist": "Sia",
        "year": 2014,
        "youtubeId": "2vjPBrBU-TM",
        "startTime": 52
    }
]